Workbook

Sheet Inputs
A1: FLOW - FX Exposure & Cross-Border Payments Model
A3: Assumption | B3: Value | D3: Calculated metric | E3: Formula / Result
A4: USD payment due | B4: 100000 | D4: Theoretical 3M forward EUR/USD | E4: =B5*(1+B7*B8)/(1+B6*B8) -> 1.1657711
A5: Current EUR/USD spot (USD per EUR) | B5: 1.16 | D5: Initial EUR equivalent | E5: =B4/B5 -> 86206.897
A6: EUR annual rate | B6: 0.02 | D6: Option premium (EUR) | E6: =E5*B10 -> 1293.1034
A7: USD annual rate | B7: 0.04 | D7: 100% forward EUR cost | E7: =B4/E4 -> 85780.13
A8: Tenor (years) | B8: 0.25
A9: Option strike EUR/USD | B9: 1.16
A10: Option premium (% initial EUR equiv.) | B10: 0.015
A11: Selected hedge ratio | B11: 0.5
A12: Illustrative payment fee | B12: 0.0025

Sheet Scenario Analysis
A1: Scenario Analysis - EUR cost of USD 100,000 payment
A3: EUR/USD at payment | B3: Unhedged cost (EUR) | C3: 100% Forward (EUR) | D3: Option hedge (EUR) | E3: 50% Forward hedge (EUR) | F3: Saving vs unhedged - Forward | G3: Saving vs unhedged - Option | H3: Saving vs unhedged - 50% hedge
A4: 1.05 | B4: =Inputs!$B$4/A4 -> 95238.095 | C4: =Inputs!$B$4/Inputs!$E$4 -> 85780.13 | D4: =MIN(Inputs!$B$4/Inputs!$B$9,Inputs!$B$4/A4)+Inputs!$E$6 -> 87500 | E4: =Inputs!$B$11*C4+(1-Inputs!$B$11)*B4 -> 90509.112 | F4: =B4-C4 -> 9457.9655 | G4: =B4-D4 -> 7738.0952 | H4: =B4-E4 -> 4728.9828
A5: 1.1 | B5: =Inputs!$B$4/A5 -> 90909.091 | C5: =Inputs!$B$4/Inputs!$E$4 -> 85780.13 | D5: =MIN(Inputs!$B$4/Inputs!$B$9,Inputs!$B$4/A5)+Inputs!$E$6 -> 87500 | E5: =Inputs!$B$11*C5+(1-Inputs!$B$11)*B5 -> 88344.61 | F5: =B5-C5 -> 5128.9612 | G5: =B5-D5 -> 3409.0909 | H5: =B5-E5 -> 2564.4806
A6: 1.16 | B6: =Inputs!$B$4/A6 -> 86206.897 | C6: =Inputs!$B$4/Inputs!$E$4 -> 85780.13 | D6: =MIN(Inputs!$B$4/Inputs!$B$9,Inputs!$B$4/A6)+Inputs!$E$6 -> 87500 | E6: =Inputs!$B$11*C6+(1-Inputs!$B$11)*B6 -> 85993.513 | F6: =B6-C6 -> 426.76681 | G6: =B6-D6 -> -1293.1034 | H6: =B6-E6 -> 213.38341
A7: 1.22 | B7: =Inputs!$B$4/A7 -> 81967.213 | C7: =Inputs!$B$4/Inputs!$E$4 -> 85780.13 | D7: =MIN(Inputs!$B$4/Inputs!$B$9,Inputs!$B$4/A7)+Inputs!$E$6 -> 83260.317 | E7: =Inputs!$B$11*C7+(1-Inputs!$B$11)*B7 -> 83873.671 | F7: =B7-C7 -> -3812.9166 | G7: =B7-D7 -> -1293.1034 | H7: =B7-E7 -> -1906.4583
A8: 1.28 | B8: =Inputs!$B$4/A8 -> 78125 | C8: =Inputs!$B$4/Inputs!$E$4 -> 85780.13 | D8: =MIN(Inputs!$B$4/Inputs!$B$9,Inputs!$B$4/A8)+Inputs!$E$6 -> 79418.103 | E8: =Inputs!$B$11*C8+(1-Inputs!$B$11)*B8 -> 81952.565 | F8: =B8-C8 -> -7655.1297 | G8: =B8-D8 -> -1293.1034 | H8: =B8-E8 -> -3827.5649
A10: Interpretation
A11: EUR weakens (EUR/USD falls) | B11: Unhedged payment becomes more expensive in EUR; forward gives budget certainty.
A12: EUR strengthens (EUR/USD rises) | B12: Unhedged benefits; option can preserve upside after paying the premium.
A13: Partial hedge | B13: Balances certainty and flexibility; the hedge ratio can be changed in Inputs.

Sheet Dashboard
A1: FLOW - Treasury Decision Dashboard
A3: KPI | B3: Value
A4: USD exposure | B4: =Inputs!B4 -> 100000
A5: 3M forward EUR/USD | B5: =Inputs!E4 -> 1.1657711
A6: Forward EUR budget | B6: =Inputs!E7 -> 85780.13
A7: Selected hedge ratio | B7: =Inputs!B11 -> 0.5
A9: Decision guide
A10: Priority = certainty | B10: Use a higher forward hedge ratio to lock the EUR cost.
A11: Priority = upside participation | B11: Option hedge protects against adverse FX while retaining benefit if EUR strengthens, net of premium.
A12: Priority = compromise | B12: A partial hedge reduces FX sensitivity while preserving some flexibility.
